[{"id":"9e74ab260de20148172f83c929a0ee3e","sport_key":"basketball_nba","sport_nice":"NBA","teams":["Chicago Bulls","Indiana Pacers"],"home_team":"Indiana Pacers","commence_time":"2021-04-06T23:10:18Z","sites":[{"site_key":"fanduel","site_nice":"FanDuel","last_update":"2021-04-06T23:28:20Z","odds":{"spreads":{"odds":[-106,-120],"points":["-2.5","2.5"]}}},{"site_key":"betmgm","site_nice":"BetMGM","last_update":"2021-04-06T23:28:29Z","odds":{"spreads":{"odds":[-115,-110],"points":["-1.5","1.5"]}}},{"site_key":"pointsbetus","site_nice":"PointsBet (US)","last_update":"2021-04-06T23:28:27Z","odds":{"spreads":{"odds":[105,-125],"points":["-1.5","1.5"]}}},{"site_key":"foxbet","site_nice":"FOX Bet","last_update":"2021-04-06T23:28:37Z","odds":{"spreads":{"odds":[-110,-110],"points":["-0.5","0.5"]}}},{"site_key":"unibet","site_nice":"Unibet","last_update":"2021-04-06T23:28:17Z","odds":{"spreads":{"odds":[-114,-111],"points":["-2.0","2.0"]}}},{"site_key":"betrivers","site_nice":"BetRivers","last_update":"2021-04-06T23:28:19Z","odds":{"spreads":{"odds":[-114,-112],"points":["-2.0","2.0"]}}},{"site_key":"sugarhouse","site_nice":"SugarHouse","last_update":"2021-04-06T23:28:22Z","odds":{"spreads":{"odds":[-114,-112],"points":["-2.0","2.0"]}}},{"site_key":"draftkings","site_nice":"DraftKings","last_update":"2021-04-06T23:28:14Z","odds":{"spreads":{"odds":[-117,-109],"points":["-1.5","1.5"]}}},{"site_key":"williamhill_us","site_nice":"William Hill (US)","last_update":"2021-04-06T23:28:19Z","odds":{"spreads":{"odds":[-105,-125],"points":["-1.5","1.5"]}}},{"site_key":"mybookieag","site_nice":"MyBookie.ag","last_update":"2021-04-06T23:28:27Z","odds":{"spreads":{"odds":[-110,-110],"points":["-2.5","2.5"]}}},{"site_key":"gtbets","site_nice":"GTbets","last_update":"2021-04-06T23:28:27Z","odds":{"spreads":{"odds":[-113,-113],"points":["-1.5","1.5"]}}},{"site_key":"caesars","site_nice":"Caesars","last_update":"2021-04-06T23:28:12Z","odds":{"spreads":{"odds":[-105,-125],"points":["-1.5","1.5"]}}}],"sites_count":12},{"id":"2605983348eae282bf99ba1e1d79fe3a","sport_key":"basketball_nba","sport_nice":"NBA","teams":["Boston Celtics","Philadelphia 76ers"],"home_team":"Boston Celtics","commence_time":"2021-04-06T23:45:00Z","sites":[{"site_key":"bovada","site_nice":"Bovada","last_update":"2021-04-06T23:28:08Z","odds":{"spreads":{"odds":[-110,-110],"points":["1.0","-1.0"]}}},{"site_key":"fanduel","site_nice":"FanDuel","last_update":"2021-04-06T23:28:20Z","odds":{"spreads":{"odds":[-110,-110],"points":["1.0","-1.0"]}}},{"site_key":"pointsbetus","site_nice":"PointsBet (US)","last_update":"2021-04-06T23:28:27Z","odds":{"spreads":{"odds":[-115,-105],"points":["1.0","-1.0"]}}},{"site_key":"betonlineag","site_nice":"BetOnline.ag","last_update":"2021-04-06T23:28:17Z","odds":{"spreads":{"odds":[-102,-119],"points":["-0.0","0.0"]}}},{"site_key":"foxbet","site_nice":"FOX Bet","last_update":"2021-04-06T23:28:37Z","odds":{"spreads":{"odds":[-105,-110],"points":["0.0","-0.0"]}}},{"site_key":"gtbets","site_nice":"GTbets","last_update":"2021-04-06T23:28:27Z","odds":{"spreads":{"odds":[-109,-109],"points":["0","0"]}}},{"site_key":"caesars","site_nice":"Caesars","last_update":"2021-04-06T23:28:12Z","odds":{"spreads":{"odds":[-110,-110],"points":["0.0","0.0"]}}},{"site_key":"williamhill_us","site_nice":"William Hill (US)","last_update":"2021-04-06T23:28:19Z","odds":{"spreads":{"odds":[-110,-110],"points":["0.0","-0.0"]}}},{"site_key":"betmgm","site_nice":"BetMGM","last_update":"2021-04-06T23:28:29Z","odds":{"spreads":{"odds":[-110,-110],"points":["1.5","-1.5"]}}},{"site_key":"betrivers","site_nice":"BetRivers","last_update":"2021-04-06T23:28:19Z","odds":{"spreads":{"odds":[-110,-112],"points":["1.5","-1.5"]}}},{"site_key":"sugarhouse","site_nice":"SugarHouse","last_update":"2021-04-06T23:28:22Z","odds":{"spreads":{"odds":[-110,-112],"points":["1.5","-1.5"]}}},{"site_key":"unibet","site_nice":"Unibet","last_update":"2021-04-06T23:28:17Z","odds":{"spreads":{"odds":[-110,-111],"points":["1.5","-1.5"]}}},{"site_key":"draftkings","site_nice":"DraftKings","last_update":"2021-04-06T23:28:14Z","odds":{"spreads":{"odds":[-110,-112],"points":["1.5","-1.5"]}}},{"site_key":"mybookieag","site_nice":"MyBookie.ag","last_update":"2021-04-06T23:28:27Z","odds":{"spreads":{"odds":[-110,-110],"points":["1.5","-1.5"]}}},{"site_key":"intertops","site_nice":"Intertops","last_update":"2021-04-06T23:17:27Z","odds":{"spreads":{"odds":[-110,-110],"points":["1.00","-1.00"]}}}],"sites_count":15},{"id":"246ea5e4e4b52fec716f3500c61e1743","sport_key":"basketball_nba","sport_nice":"NBA","teams":["Atlanta Hawks","New Orleans Pelicans"],"home_team":"Atlanta Hawks","commence_time":"2021-04-06T23:45:00Z","sites":[{"site_key":"fanduel","site_nice":"FanDuel","last_update":"2021-04-06T23:28:20Z","odds":{"spreads":{"odds":[-110,-110],"points":["-3.5","3.5"]}}},{"site_key":"betmgm","site_nice":"BetMGM","last_update":"2021-04-06T23:28:29Z","odds":{"spreads":{"odds":[-110,-110],"points":["-3.5","3.5"]}}},{"site_key":"foxbet","site_nice":"FOX Bet","last_update":"2021-04-06T23:28:37Z","odds":{"spreads":{"odds":[-110,-105],"points":["-3.5","3.5"]}}},{"site_key":"pointsbetus","site_nice":"PointsBet (US)","last_update":"2021-04-06T23:28:27Z","odds":{"spreads":{"odds":[-110,-110],"points":["-3.5","3.5"]}}},{"site_key":"unibet","site_nice":"Unibet","last_update":"2021-04-06T23:28:17Z","odds":{"spreads":{"odds":[-106,-114],"points":["-4.0","4.0"]}}},{"site_key":"betrivers","site_nice":"BetRivers","last_update":"2021-04-06T23:28:19Z","odds":{"spreads":{"odds":[-107,-114],"points":["-4.0","4.0"]}}},{"site_key":"sugarhouse","site_nice":"SugarHouse","last_update":"2021-04-06T23:28:22Z","odds":{"spreads":{"odds":[-107,-114],"points":["-4.0","4.0"]}}},{"site_key":"draftkings","site_nice":"DraftKings","last_update":"2021-04-06T23:28:14Z","odds":{"spreads":{"odds":[-107,-114],"points":["-4.0","4.0"]}}},{"site_key":"williamhill_us","site_nice":"William Hill (US)","last_update":"2021-04-06T23:28:19Z","odds":{"spreads":{"odds":[-110,-110],"points":["-3.5","3.5"]}}},{"site_key":"betonlineag","site_nice":"BetOnline.ag","last_update":"2021-04-06T23:28:17Z","odds":{"spreads":{"odds":[-111,-111],"points":["-3.5","3.5"]}}},{"site_key":"bovada","site_nice":"Bovada","last_update":"2021-04-06T23:28:08Z","odds":{"spreads":{"odds":[-110,-110],"points":["-3.5","3.5"]}}},{"site_key":"mybookieag","site_nice":"MyBookie.ag","last_update":"2021-04-06T23:28:27Z","odds":{"spreads":{"odds":[-110,-110],"points":["-4.0","4.0"]}}},{"site_key":"intertops","site_nice":"Intertops","last_update":"2021-04-06T23:28:27Z","odds":{"spreads":{"odds":[-110,-110],"points":["-3.50","3.50"]}}},{"site_key":"gtbets","site_nice":"GTbets","last_update":"2021-04-06T23:28:27Z","odds":{"spreads":{"odds":[-109,-109],"points":["-3.5","3.5"]}}},{"site_key":"caesars","site_nice":"Caesars","last_update":"2021-04-06T23:28:12Z","odds":{"spreads":{"odds":[-110,-110],"points":["-3.5","3.5"]}}}],"sites_count":15},{"id":"74de59285687c4a5b2a09f79207175af","sport_key":"basketball_nba","sport_nice":"NBA","teams":["Los Angeles Lakers","Toronto Raptors"],"home_team":"Toronto Raptors","commence_time":"2021-04-06T23:45:00Z","sites":[{"site_key":"fanduel","site_nice":"FanDuel","last_update":"2021-04-06T23:28:20Z","odds":{"spreads":{"odds":[-110,-110],"points":["-1.5","1.5"]}}},{"site_key":"betmgm","site_nice":"BetMGM","last_update":"2021-04-06T23:28:29Z","odds":{"spreads":{"odds":[-110,-110],"points":["-1.5","1.5"]}}},{"site_key":"pointsbetus","site_nice":"PointsBet (US)","last_update":"2021-04-06T23:28:27Z","odds":{"spreads":{"odds":[-110,-110],"points":["-1.0","1.0"]}}},{"site_key":"foxbet","site_nice":"FOX Bet","last_update":"2021-04-06T23:28:37Z","odds":{"spreads":{"odds":[-110,-110],"points":["-1.5","1.5"]}}},{"site_key":"betrivers","site_nice":"BetRivers","last_update":"2021-04-06T23:28:19Z","odds":{"spreads":{"odds":[-112,-110],"points":["-1.5","1.5"]}}},{"site_key":"sugarhouse","site_nice":"SugarHouse","last_update":"2021-04-06T23:28:22Z","odds":{"spreads":{"odds":[-112,-110],"points":["-1.5","1.5"]}}},{"site_key":"draftkings","site_nice":"DraftKings","last_update":"2021-04-06T23:28:14Z","odds":{"spreads":{"odds":[-112,-110],"points":["-1.5","1.5"]}}},{"site_key":"unibet","site_nice":"Unibet","last_update":"2021-04-06T23:28:17Z","odds":{"spreads":{"odds":[-111,-110],"points":["-1.5","1.5"]}}},{"site_key":"betonlineag","site_nice":"BetOnline.ag","last_update":"2021-04-06T23:28:17Z","odds":{"spreads":{"odds":[-111,-111],"points":["-1.0","1.0"]}}},{"site_key":"williamhill_us","site_nice":"William Hill (US)","last_update":"2021-04-06T23:28:19Z","odds":{"spreads":{"odds":[-110,-110],"points":["-1.0","1.0"]}}},{"site_key":"bovada","site_nice":"Bovada","last_update":"2021-04-06T23:28:08Z","odds":{"spreads":{"odds":[-115,-105],"points":["-1.0","1.0"]}}},{"site_key":"mybookieag","site_nice":"MyBookie.ag","last_update":"2021-04-06T23:28:27Z","odds":{"spreads":{"odds":[-110,-110],"points":["-1.5","1.5"]}}},{"site_key":"gtbets","site_nice":"GTbets","last_update":"2021-04-06T23:28:27Z","odds":{"spreads":{"odds":[-109,-109],"points":["-1","1"]}}},{"site_key":"intertops","site_nice":"Intertops","last_update":"2021-04-06T23:28:27Z","odds":{"spreads":{"odds":[-110,-110],"points":["-1.00","1.00"]}}},{"site_key":"caesars","site_nice":"Caesars","last_update":"2021-04-06T23:28:12Z","odds":{"spreads":{"odds":[-110,-110],"points":["-1.0","1.0"]}}}],"sites_count":15},{"id":"073361326c555683babafb6e79dc0e79","sport_key":"basketball_nba","sport_nice":"NBA","teams":["Memphis Grizzlies","Miami Heat"],"home_team":"Miami Heat","commence_time":"2021-04-07T00:15:00Z","sites":[{"site_key":"fanduel","site_nice":"FanDuel","last_update":"2021-04-06T23:28:20Z","odds":{"spreads":{"odds":[-114,-106],"points":["6.5","-6.5"]}}},{"site_key":"bovada","site_nice":"Bovada","last_update":"2021-04-06T23:28:08Z","odds":{"spreads":{"odds":[-105,-115],"points":["6.0","-6.0"]}}},{"site_key":"betonlineag","site_nice":"BetOnline.ag","last_update":"2021-04-06T23:28:17Z","odds":{"spreads":{"odds":[-105,-115],"points":["6.0","-6.0"]}}},{"site_key":"pointsbetus","site_nice":"PointsBet (US)","last_update":"2021-04-06T23:28:27Z","odds":{"spreads":{"odds":[-105,-115],"points":["6.0","-6.0"]}}},{"site_key":"foxbet","site_nice":"FOX Bet","last_update":"2021-04-06T23:28:37Z","odds":{"spreads":{"odds":[-110,-110],"points":["6.0","-6.0"]}}},{"site_key":"williamhill_us","site_nice":"William Hill (US)","last_update":"2021-04-06T23:28:19Z","odds":{"spreads":{"odds":[-110,-110],"points":["6.0","-6.0"]}}},{"site_key":"caesars","site_nice":"Caesars","last_update":"2021-04-06T23:28:12Z","odds":{"spreads":{"odds":[-110,-110],"points":["6.0","-6.0"]}}},{"site_key":"sugarhouse","site_nice":"SugarHouse","last_update":"2021-04-06T23:28:22Z","odds":{"spreads":{"odds":[-110,-110],"points":["6.0","-6.0"]}}},{"site_key":"unibet","site_nice":"Unibet","last_update":"2021-04-06T23:28:17Z","odds":{"spreads":{"odds":[-110,-110],"points":["6.0","-6.0"]}}},{"site_key":"betrivers","site_nice":"BetRivers","last_update":"2021-04-06T23:28:19Z","odds":{"spreads":{"odds":[-110,-110],"points":["6.0","-6.0"]}}},{"site_key":"draftkings","site_nice":"DraftKings","last_update":"2021-04-06T23:28:14Z","odds":{"spreads":{"odds":[-110,-110],"points":["6.0","-6.0"]}}},{"site_key":"gtbets","site_nice":"GTbets","last_update":"2021-04-06T23:28:27Z","odds":{"spreads":{"odds":[-109,-109],"points":["6","-6"]}}},{"site_key":"betmgm","site_nice":"BetMGM","last_update":"2021-04-06T23:28:29Z","odds":{"spreads":{"odds":[-110,-110],"points":["6.0","-6.0"]}}},{"site_key":"mybookieag","site_nice":"MyBookie.ag","last_update":"2021-04-06T23:28:27Z","odds":{"spreads":{"odds":[-110,-110],"points":["6.0","-6.0"]}}},{"site_key":"intertops","site_nice":"Intertops","last_update":"2021-04-06T23:28:27Z","odds":{"spreads":{"odds":[-110,-110],"points":["6.00","-6.00"]}}}],"sites_count":15},{"id":"aca79c40925ed104552907f77c51a97d","sport_key":"basketball_nba","sport_nice":"NBA","teams":["Denver Nuggets","Detroit Pistons"],"home_team":"Denver Nuggets","commence_time":"2021-04-07T01:15:00Z","sites":[{"site_key":"fanduel","site_nice":"FanDuel","last_update":"2021-04-06T23:28:20Z","odds":{"spreads":{"odds":[-110,-110],"points":["-12.5","12.5"]}}},{"site_key":"betmgm","site_nice":"BetMGM","last_update":"2021-04-06T23:28:29Z","odds":{"spreads":{"odds":[-110,-110],"points":["-12.5","12.5"]}}},{"site_key":"pointsbetus","site_nice":"PointsBet (US)","last_update":"2021-04-06T23:28:27Z","odds":{"spreads":{"odds":[-110,-110],"points":["-12.5","12.5"]}}},{"site_key":"betrivers","site_nice":"BetRivers","last_update":"2021-04-06T23:28:19Z","odds":{"spreads":{"odds":[-112,-110],"points":["-12.5","12.5"]}}},{"site_key":"sugarhouse","site_nice":"SugarHouse","last_update":"2021-04-06T23:28:22Z","odds":{"spreads":{"odds":[-112,-110],"points":["-12.5","12.5"]}}},{"site_key":"draftkings","site_nice":"DraftKings","last_update":"2021-04-06T23:28:14Z","odds":{"spreads":{"odds":[-112,-110],"points":["-12.5","12.5"]}}},{"site_key":"unibet","site_nice":"Unibet","last_update":"2021-04-06T23:28:17Z","odds":{"spreads":{"odds":[-111,-110],"points":["-12.5","12.5"]}}},{"site_key":"foxbet","site_nice":"FOX Bet","last_update":"2021-04-06T23:28:37Z","odds":{"spreads":{"odds":[-110,-110],"points":["-12.0","12.0"]}}},{"site_key":"williamhill_us","site_nice":"William Hill (US)","last_update":"2021-04-06T23:28:19Z","odds":{"spreads":{"odds":[-110,-110],"points":["-12.5","12.5"]}}},{"site_key":"betonlineag","site_nice":"BetOnline.ag","last_update":"2021-04-06T23:28:17Z","odds":{"spreads":{"odds":[-111,-110],"points":["-12.0","12.0"]}}},{"site_key":"bovada","site_nice":"Bovada","last_update":"2021-04-06T23:28:08Z","odds":{"spreads":{"odds":[-115,-105],"points":["-12.0","12.0"]}}},{"site_key":"mybookieag","site_nice":"MyBookie.ag","last_update":"2021-04-06T23:28:27Z","odds":{"spreads":{"odds":[-110,-110],"points":["-12.5","12.5"]}}},{"site_key":"gtbets","site_nice":"GTbets","last_update":"2021-04-06T23:28:27Z","odds":{"spreads":{"odds":[-109,-109],"points":["-12.5","12.5"]}}},{"site_key":"intertops","site_nice":"Intertops","last_update":"2021-04-06T23:28:27Z","odds":{"spreads":{"odds":[-110,-110],"points":["-12.00","12.00"]}}},{"site_key":"caesars","site_nice":"Caesars","last_update":"2021-04-06T23:28:12Z","odds":{"spreads":{"odds":[-110,-110],"points":["-12.5","12.5"]}}}],"sites_count":15},{"id":"1de447ffc0f8ebc7515c444bb38f8dfa","sport_key":"basketball_nba","sport_nice":"NBA","teams":["Los Angeles Clippers","Portland Trail Blazers"],"home_team":"Los Angeles Clippers","commence_time":"2021-04-07T02:15:00Z","sites":[{"site_key":"gtbets","site_nice":"GTbets","last_update":"2021-04-06T23:28:27Z","odds":{"spreads":{"odds":[-109,-109],"points":["-6","6"]}}},{"site_key":"fanduel","site_nice":"FanDuel","last_update":"2021-04-06T23:28:20Z","odds":{"spreads":{"odds":[-115,-105],"points":["-6.0","6.0"]}}},{"site_key":"betonlineag","site_nice":"BetOnline.ag","last_update":"2021-04-06T23:28:17Z","odds":{"spreads":{"odds":[-119,-102],"points":["-6.0","6.0"]}}},{"site_key":"foxbet","site_nice":"FOX Bet","last_update":"2021-04-06T23:28:37Z","odds":{"spreads":{"odds":[-110,-110],"points":["-6.0","6.0"]}}},{"site_key":"williamhill_us","site_nice":"William Hill (US)","last_update":"2021-04-06T23:28:19Z","odds":{"spreads":{"odds":[-110,-110],"points":["-6.0","6.0"]}}},{"site_key":"bovada","site_nice":"Bovada","last_update":"2021-04-06T23:28:08Z","odds":{"spreads":{"odds":[-105,-115],"points":["-6.0","6.0"]}}},{"site_key":"pointsbetus","site_nice":"PointsBet (US)","last_update":"2021-04-06T23:28:27Z","odds":{"spreads":{"odds":[-110,-110],"points":["-6.0","6.0"]}}},{"site_key":"betmgm","site_nice":"BetMGM","last_update":"2021-04-06T23:28:29Z","odds":{"spreads":{"odds":[-110,-110],"points":["-6.0","6.0"]}}},{"site_key":"sugarhouse","site_nice":"SugarHouse","last_update":"2021-04-06T23:28:22Z","odds":{"spreads":{"odds":[-114,-107],"points":["-6.0","6.0"]}}},{"site_key":"unibet","site_nice":"Unibet","last_update":"2021-04-06T23:28:17Z","odds":{"spreads":{"odds":[-114,-106],"points":["-6.0","6.0"]}}},{"site_key":"betrivers","site_nice":"BetRivers","last_update":"2021-04-06T23:28:19Z","odds":{"spreads":{"odds":[-114,-107],"points":["-6.0","6.0"]}}},{"site_key":"draftkings","site_nice":"DraftKings","last_update":"2021-04-06T23:28:14Z","odds":{"spreads":{"odds":[-114,-107],"points":["-6.0","6.0"]}}},{"site_key":"mybookieag","site_nice":"MyBookie.ag","last_update":"2021-04-06T23:28:27Z","odds":{"spreads":{"odds":[-110,-110],"points":["-6.0","6.0"]}}},{"site_key":"intertops","site_nice":"Intertops","last_update":"2021-04-06T23:28:27Z","odds":{"spreads":{"odds":[-110,-110],"points":["-6.00","6.00"]}}}],"sites_count":14},{"id":"832c00b8da90c9e724f53f8fc914a3cc","sport_key":"basketball_nba","sport_nice":"NBA","teams":["Golden State Warriors","Milwaukee Bucks"],"home_team":"Golden State Warriors","commence_time":"2021-04-07T02:15:00Z","sites":[{"site_key":"fanduel","site_nice":"FanDuel","last_update":"2021-04-06T23:28:20Z","odds":{"spreads":{"odds":[-110,-110],"points":["6.5","-6.5"]}}},{"site_key":"betmgm","site_nice":"BetMGM","last_update":"2021-04-06T23:28:29Z","odds":{"spreads":{"odds":[-110,-110],"points":["6.5","-6.5"]}}},{"site_key":"pointsbetus","site_nice":"PointsBet (US)","last_update":"2021-04-06T23:28:27Z","odds":{"spreads":{"odds":[-110,-110],"points":["6.5","-6.5"]}}},{"site_key":"foxbet","site_nice":"FOX Bet","last_update":"2021-04-06T23:28:37Z","odds":{"spreads":{"odds":[-118,100],"points":["6.5","-6.5"]}}},{"site_key":"betrivers","site_nice":"BetRivers","last_update":"2021-04-06T23:28:19Z","odds":{"spreads":{"odds":[-112,-110],"points":["6.5","-6.5"]}}},{"site_key":"sugarhouse","site_nice":"SugarHouse","last_update":"2021-04-06T23:28:22Z","odds":{"spreads":{"odds":[-112,-110],"points":["6.5","-6.5"]}}},{"site_key":"draftkings","site_nice":"DraftKings","last_update":"2021-04-06T23:28:14Z","odds":{"spreads":{"odds":[-112,-110],"points":["6.5","-6.5"]}}},{"site_key":"unibet","site_nice":"Unibet","last_update":"2021-04-06T23:28:17Z","odds":{"spreads":{"odds":[-111,-110],"points":["6.5","-6.5"]}}},{"site_key":"betonlineag","site_nice":"BetOnline.ag","last_update":"2021-04-06T23:28:17Z","odds":{"spreads":{"odds":[-111,-111],"points":["6.5","-6.5"]}}},{"site_key":"williamhill_us","site_nice":"William Hill (US)","last_update":"2021-04-06T23:28:19Z","odds":{"spreads":{"odds":[-110,-110],"points":["6.5","-6.5"]}}},{"site_key":"bovada","site_nice":"Bovada","last_update":"2021-04-06T23:28:08Z","odds":{"spreads":{"odds":[-110,-110],"points":["6.5","-6.5"]}}},{"site_key":"mybookieag","site_nice":"MyBookie.ag","last_update":"2021-04-06T23:28:27Z","odds":{"spreads":{"odds":[-105,-115],"points":["6.5","-6.5"]}}},{"site_key":"gtbets","site_nice":"GTbets","last_update":"2021-04-06T23:28:27Z","odds":{"spreads":{"odds":[-109,-109],"points":["6.5","-6.5"]}}},{"site_key":"intertops","site_nice":"Intertops","last_update":"2021-04-06T23:28:27Z","odds":{"spreads":{"odds":[-110,-110],"points":["6.50","-6.50"]}}}],"sites_count":14}]